hydrostats/__init__.py
hydrostats/analyze.py
hydrostats/data.py
hydrostats/ens_metrics.py
hydrostats/metrics.py
hydrostats/py.typed
hydrostats/typing_aliases.py
hydrostats/visual.py
hydrostats-1.0.0.dist-info/WHEEL
hydrostats-1.0.0.dist-info/METADATA
hydrostats-1.0.0.dist-info/RECORD
