Metadata-Version: 2.3
Name: hydrostats
Version: 1.0.0
Summary: Tools for use in comparison studies, specifically for use in the field of hydrology
Keywords: hydrology,error,metrics,comparison,statistics,forecast,observed
Author: Wade Roberts
Author-email: Wade Roberts <wade.a.roberts@protonmail.com>
License: MIT
Classifier: Programming Language :: Python :: 3.10
Classifier: Programming Language :: Python :: 3.11
Classifier: Programming Language :: Python :: 3.12
Classifier: Programming Language :: Python :: 3.13
Classifier: Programming Language :: Python :: 3.14
Classifier: Topic :: Scientific/Engineering :: Hydrology
Requires-Dist: hydroerr~=2.0
Requires-Dist: matplotlib~=3.0
Requires-Dist: numba~=0.63.0
Requires-Dist: numpy~=2.0
Requires-Dist: pandas~=2.0
Requires-Dist: scipy~=1.0
Requires-Python: >=3.10, <=3.15
Project-URL: Homepage, https://github.com/BYU-Hydroinformatics/Hydrostats
